whittaker_eilers-0.2.0.dist-info/METADATA
whittaker_eilers-0.2.0.dist-info/WHEEL
whittaker_eilers/__init__.py
whittaker_eilers/__init__.pyi
whittaker_eilers/py.typed
whittaker_eilers/whittaker_eilers.pyd
whittaker_eilers-0.2.0.dist-info/RECORD
