Metadata-Version: 2.3
Name: whittaker-eilers
Version: 0.2.0
Classifier: License :: OSI Approved :: MIT License
Classifier: Programming Language :: Rust
Classifier: Programming Language :: Python :: Implementation :: PyPy
Classifier: Topic :: Scientific/Engineering
Classifier: Intended Audience :: Science/Research
Summary: A sparse matrix implementation of Whittaker-Eilers smoothing and interpolation
Author: Andrew Bowell
Requires-Python: >=3.7
Project-URL: Repository, https://github.com/AnBowell/whittaker-eilers/tree/main/whittaker-eilers-py
Project-URL: Documentation, https://github.com/AnBowell/whittaker-eilers/tree/main/whittaker-eilers-py
